pypom.py
PyPOM_kkrenzke-0.0.0.dev7.dist-info/LICENSE
PyPOM_kkrenzke-0.0.0.dev7.dist-info/METADATA
PyPOM_kkrenzke-0.0.0.dev7.dist-info/WHEEL
PyPOM_kkrenzke-0.0.0.dev7.dist-info/top_level.txt
PyPOM_kkrenzke-0.0.0.dev7.dist-info/RECORD
